rime_sdk/__init__.py
rime_sdk/authenticator.py
rime_sdk/client.py
rime_sdk/continuous_test.py
rime_sdk/data_collector.py
rime_sdk/detection_event.py
rime_sdk/generative_firewall.py
rime_sdk/generative_model.py
rime_sdk/image_builder.py
rime_sdk/job.py
rime_sdk/monitor.py
rime_sdk/project.py
rime_sdk/registry.py
rime_sdk/schedule.py
rime_sdk/test_batch.py
rime_sdk/test_run.py
rime_sdk/internal/__init__.py
rime_sdk/internal/config_parser.py
rime_sdk/internal/constants.py
rime_sdk/internal/decorators.py
rime_sdk/internal/file_upload.py
rime_sdk/internal/rest_error_handler.py
rime_sdk/internal/swagger_parser.py
rime_sdk/internal/swagger_utils.py
rime_sdk/internal/test_helpers.py
rime_sdk/internal/throttle_queue.py
rime_sdk/internal/utils.py
rime_sdk/swagger/__init__.py
rime_sdk/swagger/swagger_client/__init__.py
rime_sdk/swagger/swagger_client/api_client.py
rime_sdk/swagger/swagger_client/configuration.py
rime_sdk/swagger/swagger_client/rest.py
rime_sdk/swagger/swagger_client/api/__init__.py
rime_sdk/swagger/swagger_client/api/agent_manager_api.py
rime_sdk/swagger/swagger_client/api/config_validator_api.py
rime_sdk/swagger/swagger_client/api/customer_managed_key_service_api.py
rime_sdk/swagger/swagger_client/api/data_collector_api.py
rime_sdk/swagger/swagger_client/api/detection_api.py
rime_sdk/swagger/swagger_client/api/feature_flag_api.py
rime_sdk/swagger/swagger_client/api/file_scanning_api.py
rime_sdk/swagger/swagger_client/api/file_upload_api.py
rime_sdk/swagger/swagger_client/api/firewall_api.py
rime_sdk/swagger/swagger_client/api/firewall_instance_manager_api.py
rime_sdk/swagger/swagger_client/api/firewall_service_api.py
rime_sdk/swagger/swagger_client/api/generative_validation_api.py
rime_sdk/swagger/swagger_client/api/image_registry_api.py
rime_sdk/swagger/swagger_client/api/integration_service_api.py
rime_sdk/swagger/swagger_client/api/job_reader_api.py
rime_sdk/swagger/swagger_client/api/model_card_service_api.py
rime_sdk-2.13.2.dist-info/LICENSE
rime_sdk-2.13.2.dist-info/METADATA
rime_sdk-2.13.2.dist-info/WHEEL
rime_sdk-2.13.2.dist-info/top_level.txt
rime_sdk-2.13.2.dist-info/RECORD
