Metadata-Version: 2.1
Name: rime-sdk
Version: 2.13.2
Summary: Package to programmatically access a RIME deployment
Classifier: License :: OSI Approved :: Apache Software License
Requires-Python: >=3.6
License-File: LICENSE
Requires-Dist: certifi
Requires-Dist: click<8.1.4,>=8.0.1
Requires-Dist: deprecated<2.0.0,>=1.0.0
Requires-Dist: importlib-metadata
Requires-Dist: numpy<2.0.0
Requires-Dist: pandas<1.5.0,>=1.1.0
Requires-Dist: protobuf
Requires-Dist: python-dateutil
Requires-Dist: requests>=2.0.0
Requires-Dist: schema
Requires-Dist: simplejson
Requires-Dist: six
Requires-Dist: tqdm
Requires-Dist: typing-extensions
Requires-Dist: urllib3
